[
    {
        "BookTitle": "The Science of Self-Empowerment: Awakening the New Human Story",
        "BookISBN13": "978-1401949327",
        "BookISBN10": 1401949320,
        "Publisher": "Hay House Inc.",
        "Pages": "320 pages",
        "Authors": "",
        "Stars": "4.7 out of 5",
        "ratings\r": 498
    },
    {
        "BookTitle": "The Telomere Effect",
        "BookISBN13": "978-1455587988",
        "BookISBN10": 1455587982,
        "Publisher": "Grand Central Publishing",
        "Pages": "416 page",
        "Authors": "",
        "Stars": "4.5 out of 5",
        "ratings\r": 867
    },
    {
        "BookTitle": "The Dominant Animal: Human Evolution and the Environment",
        "BookISBN13": "978-1597260961",
        "BookISBN10": 1597260967,
        "Publisher": "Wiley 1st edition ",
        "Pages": "446 pages",
        "Authors": "",
        "Stars": "3.6 out of  5",
        "ratings\r": 8
    }
]